setup.py
src/TUFECat/StatisticCat.py
src/TUFECat/TextAnalysisCat.py
src/TUFECat/TimeSeriseCat.py
src/TUFECat/__init__.py
src/TUFECat.egg-info/PKG-INFO
src/TUFECat.egg-info/SOURCES.txt
src/TUFECat.egg-info/dependency_links.txt
src/TUFECat.egg-info/requires.txt
src/TUFECat.egg-info/top_level.txt